yae/__init__.py
yae/__main__.py
yae/common/__init__.py
yae/common/cli.py
yae/tools/__init__.py
yae/tools/install.py
yae/tools/update.py
yae-0.0.1.dist-info/LICENSE
yae-0.0.1.dist-info/METADATA
yae-0.0.1.dist-info/WHEEL
yae-0.0.1.dist-info/top_level.txt
yae-0.0.1.dist-info/RECORD
