Metadata-Version: 2.1
Name: yae
Version: 0.0.1
Summary: DevOps Toolbox
Home-page: https://github.com/malanore-z/yae
Author: malanore
Author-email: malanore.z@gmail.com
Project-URL: Bug Tracker, https://github.com/malanore-z/yae/issues
Classifier: Intended Audience :: Developers
Classifier: Programming Language :: Python :: 3
Classifier: License :: OSI Approved :: MIT License
Classifier: Operating System :: OS Independent
Requires-Python: >=3.6
License-File: LICENSE
Requires-Dist: psutil
Requires-Dist: PyYAML
Requires-Dist: numpy
